{
    "index": {
      "type": "page",
      "title": "GitGinie",
      "display": "hidden",
      "theme": {
        "typesetting": "raw"
      }
    },
    "profile": {
        "type": "page",
        "title": "Profile",
        "theme": {
          "typesetting": "article"
        }
      },
      "repoconfig": {
        "type": "page",
        "title": "Configure Repo",
        "theme": {
          "typesetting": "article"
        }
      },
      "labelconfig": {
        "type": "page",
        "title": "Configure Label",
        "theme": {
          "typesetting": "article"
        }
      }
  }
  